aliyunsdkcams/__init__.py
aliyunsdkcams/endpoint.py
aliyunsdkcams/request/__init__.py
aliyunsdkcams/request/v20200606/AddChatappPhoneNumberRequest.py
aliyunsdkcams/request/v20200606/BeeBotAssociateRequest.py
aliyunsdkcams/request/v20200606/BeeBotChatRequest.py
aliyunsdkcams/request/v20200606/ChatappBindWabaRequest.py
aliyunsdkcams/request/v20200606/ChatappEmbedSignUpRequest.py
aliyunsdkcams/request/v20200606/ChatappMigrationRegisterRequest.py
aliyunsdkcams/request/v20200606/ChatappMigrationVerifiedRequest.py
aliyunsdkcams/request/v20200606/ChatappPhoneNumberDeregisterRequest.py
aliyunsdkcams/request/v20200606/ChatappPhoneNumberRegisterRequest.py
aliyunsdkcams/request/v20200606/ChatappSyncPhoneNumberRequest.py
aliyunsdkcams/request/v20200606/ChatappVerifyAndRegisterRequest.py
aliyunsdkcams/request/v20200606/CreateChatappMigrationInitiateRequest.py
aliyunsdkcams/request/v20200606/CreateChatappTemplateRequest.py
aliyunsdkcams/request/v20200606/CreateFlowRequest.py
aliyunsdkcams/request/v20200606/CreatePhoneMessageQrdlRequest.py
aliyunsdkcams/request/v20200606/DeleteChatappTemplateRequest.py
aliyunsdkcams/request/v20200606/DeleteFlowRequest.py
aliyunsdkcams/request/v20200606/DeletePhoneMessageQrdlRequest.py
aliyunsdkcams/request/v20200606/DeprecateFlowRequest.py
aliyunsdkcams/request/v20200606/EnableWhatsappROIMetricRequest.py
aliyunsdkcams/request/v20200606/GetChatappPhoneNumberMetricRequest.py
aliyunsdkcams/request/v20200606/GetChatappTemplateDetailRequest.py
aliyunsdkcams/request/v20200606/GetChatappTemplateMetricRequest.py
aliyunsdkcams/request/v20200606/GetChatappUploadAuthorizationRequest.py
aliyunsdkcams/request/v20200606/GetChatappVerifyCodeRequest.py
aliyunsdkcams/request/v20200606/GetCommerceSettingRequest.py
aliyunsdkcams/request/v20200606/GetConversationalAutomationRequest.py
aliyunsdkcams/request/v20200606/GetFlowJSONAssestRequest.py
aliyunsdkcams/request/v20200606/GetFlowPreviewUrlRequest.py
aliyunsdkcams/request/v20200606/GetFlowRequest.py
aliyun_python_sdk_cams-1.0.13.dist-info/LICENSE
aliyun_python_sdk_cams-1.0.13.dist-info/METADATA
aliyun_python_sdk_cams-1.0.13.dist-info/WHEEL
aliyun_python_sdk_cams-1.0.13.dist-info/top_level.txt
aliyun_python_sdk_cams-1.0.13.dist-info/RECORD
